[
  {
    "currency": "AED",
    "conversion": "3.672804"
  },
  {
    "currency": "AFN",
    "conversion": "69.089996"
  },
  {
    "currency": "ALL",
    "conversion": "106.599998"
  },
  {
    "currency": "AMD",
    "conversion": "480.540009"
  },
  {
    "currency": "ANG",
    "conversion": "1.780403"
  },
  {
    "currency": "AOA",
    "conversion": "206.873993"
  },
  {
    "currency": "ARS",
    "conversion": "19.450001"
  },
  {
    "currency": "AUD",
    "conversion": "1.259704"
  },
  {
    "currency": "AWG",
    "conversion": "1.7825"
  },
  {
    "currency": "AZN",
    "conversion": "1.699604"
  },
  {
    "currency": "BAM",
    "conversion": "1.571804"
  },
  {
    "currency": "BBD",
    "conversion": "2"
  },
  {
    "currency": "BDT",
    "conversion": "82.870003"
  },
  {
    "currency": "BGN",
    "conversion": "1.565704"
  },
  {
    "currency": "BHD",
    "conversion": "0.376904"
  },
  {
    "currency": "BIF",
    "conversion": "1750.97998"
  },
  {
    "currency": "BMD",
    "conversion": "1"
  },
  {
    "currency": "BND",
    "conversion": "1.319204"
  },
  {
    "currency": "BOB",
    "conversion": "6.860399"
  },
  {
    "currency": "BRL",
    "conversion": "3.218041"
  },
  {
    "currency": "BSD",
    "conversion": "1"
  },
  {
    "currency": "BTC",
    "conversion": "0.000111"
  },
  {
    "currency": "BTN",
    "conversion": "63.700001"
  },
  {
    "currency": "BWP",
    "conversion": "9.555204"
  },
  {
    "currency": "BYN",
    "conversion": "1.970398"
  },
  {
    "currency": "BYR",
    "conversion": "19600"
  },
  {
    "currency": "BZD",
    "conversion": "1.997804"
  },
  {
    "currency": "CAD",
    "conversion": "1.242104"
  },
  {
    "currency": "CDF",
    "conversion": "1565.50392"
  },
  {
    "currency": "CHF",
    "conversion": "0.930704"
  },
  {
    "currency": "CLF",
    "conversion": "0.02222"
  },
  {
    "currency": "CLP",
    "conversion": "602.750396"
  },
  {
    "currency": "CNY",
    "conversion": "6.298304"
  },
  {
    "currency": "COP",
    "conversion": "2839"
  },
  {
    "currency": "CRC",
    "conversion": "566.309998"
  },
  {
    "currency": "CUC",
    "conversion": "1"
  },
  {
    "currency": "CUP",
    "conversion": "26.5"
  },
  {
    "currency": "CVE",
    "conversion": "88.489998"
  },
  {
    "currency": "CZK",
    "conversion": "20.22204"
  },
  {
    "currency": "DJF",
    "conversion": "177.600006"
  },
  {
    "currency": "DKK",
    "conversion": "5.97404"
  },
  {
    "currency": "DOP",
    "conversion": "48.730393"
  },
  {
    "currency": "DZD",
    "conversion": "113.196999"
  },
  {
    "currency": "EGP",
    "conversion": "17.629999"
  },
  {
    "currency": "ERN",
    "conversion": "15.290392"
  },
  {
    "currency": "ETB",
    "conversion": "27.200001"
  },
  {
    "currency": "EUR",
    "conversion": "0.802304"
  },
  {
    "currency": "FJD",
    "conversion": "1.985504"
  },
  {
    "currency": "FKP",
    "conversion": "0.707604"
  },
  {
    "currency": "GBP",
    "conversion": "0.70808"
  },
  {
    "currency": "GEL",
    "conversion": "2.464904"
  },
  {
    "currency": "GGP",
    "conversion": "0.708125"
  },
  {
    "currency": "GHS",
    "conversion": "4.478504"
  },
  {
    "currency": "GIP",
    "conversion": "0.707904"
  },
  {
    "currency": "GMD",
    "conversion": "47.049999"
  },
  {
    "currency": "GNF",
    "conversion": "9004.000355"
  },
  {
    "currency": "GTQ",
    "conversion": "7.33604"
  },
  {
    "currency": "GYD",
    "conversion": "204.889999"
  },
  {
    "currency": "HKD",
    "conversion": "7.820104"
  },
  {
    "currency": "HNL",
    "conversion": "23.51804"
  },
  {
    "currency": "HRK",
    "conversion": "5.974104"
  },
  {
    "currency": "HTG",
    "conversion": "63.200001"
  },
  {
    "currency": "HUF",
    "conversion": "248.460007"
  },
  {
    "currency": "IDR",
    "conversion": "13448"
  },
  {
    "currency": "ILS",
    "conversion": "3.446104"
  },
  {
    "currency": "IMP",
    "conversion": "0.708125"
  },
  {
    "currency": "INR",
    "conversion": "64.119003"
  },
  {
    "currency": "IQD",
    "conversion": "1184"
  },
  {
    "currency": "IRR",
    "conversion": "36952.000352"
  },
  {
    "currency": "ISK",
    "conversion": "100.349998"
  },
  {
    "currency": "JEP",
    "conversion": "0.708125"
  },
  {
    "currency": "JMD",
    "conversion": "124.160004"
  },
  {
    "currency": "JOD",
    "conversion": "0.706804"
  },
  {
    "currency": "JPY",
    "conversion": "110.029999"
  },
  {
    "currency": "KES",
    "conversion": "101.449997"
  },
  {
    "currency": "KGS",
    "conversion": "68.440002"
  },
  {
    "currency": "KHR",
    "conversion": "4001.000351"
  },
  {
    "currency": "KMF",
    "conversion": "395.399994"
  },
  {
    "currency": "KPW",
    "conversion": "900.00035"
  },
  {
    "currency": "KRW",
    "conversion": "1088.503792"
  },
  {
    "currency": "KWD",
    "conversion": "0.299404"
  },
  {
    "currency": "KYD",
    "conversion": "0.820383"
  },
  {
    "currency": "KZT",
    "conversion": "321.910004"
  },
  {
    "currency": "LAK",
    "conversion": "8281.000349"
  },
  {
    "currency": "LBP",
    "conversion": "1505.503779"
  },
  {
    "currency": "LKR",
    "conversion": "154.050003"
  },
  {
    "currency": "LRD",
    "conversion": "120.300003"
  },
  {
    "currency": "LSL",
    "conversion": "12.070382"
  },
  {
    "currency": "LTL",
    "conversion": "3.048704"
  },
  {
    "currency": "LVL",
    "conversion": "0.62055"
  },
  {
    "currency": "LYD",
    "conversion": "1.324804"
  },
  {
    "currency": "MAD",
    "conversion": "8.934204"
  },
  {
    "currency": "MDL",
    "conversion": "16.790001"
  },
  {
    "currency": "MGA",
    "conversion": "3190.000347"
  },
  {
    "currency": "MKD",
    "conversion": "49.139999"
  },
  {
    "currency": "MMK",
    "conversion": "1327.503753"
  },
  {
    "currency": "MNT",
    "conversion": "2413.000346"
  },
  {
    "currency": "MOP",
    "conversion": "8.049204"
  },
  {
    "currency": "MRO",
    "conversion": "349.000346"
  },
  {
    "currency": "MUR",
    "conversion": "31.903743"
  },
  {
    "currency": "MVR",
    "conversion": "15.350378"
  },
  {
    "currency": "MWK",
    "conversion": "713.47998"
  },
  {
    "currency": "MXN",
    "conversion": "18.587999"
  },
  {
    "currency": "MYR",
    "conversion": "3.885039"
  },
  {
    "currency": "MZN",
    "conversion": "60.169998"
  },
  {
    "currency": "NAD",
    "conversion": "12.065039"
  },
  {
    "currency": "NGN",
    "conversion": "357.000344"
  },
  {
    "currency": "NIO",
    "conversion": "30.959999"
  },
  {
    "currency": "NOK",
    "conversion": "7.734039"
  },
  {
    "currency": "NPR",
    "conversion": "102.50372"
  },
  {
    "currency": "NZD",
    "conversion": "1.368804"
  },
  {
    "currency": "OMR",
    "conversion": "0.384804"
  },
  {
    "currency": "PAB",
    "conversion": "1"
  },
  {
    "currency": "PEN",
    "conversion": "3.216504"
  },
  {
    "currency": "PGK",
    "conversion": "3.150375"
  },
  {
    "currency": "PHP",
    "conversion": "51.619999"
  },
  {
    "currency": "PKR",
    "conversion": "110.419998"
  },
  {
    "currency": "PLN",
    "conversion": "3.344038"
  },
  {
    "currency": "PYG",
    "conversion": "5593.000341"
  },
  {
    "currency": "QAR",
    "conversion": "3.639804"
  },
  {
    "currency": "RON",
    "conversion": "3.704604"
  },
  {
    "currency": "RSD",
    "conversion": "94.709503"
  },
  {
    "currency": "RUB",
    "conversion": "56.521999"
  },
  {
    "currency": "RWF",
    "conversion": "835.75"
  },
  {
    "currency": "SAR",
    "conversion": "3.749904"
  },
  {
    "currency": "SBD",
    "conversion": "7.734404"
  },
  {
    "currency": "SCR",
    "conversion": "13.630372"
  },
  {
    "currency": "SDG",
    "conversion": "17.910372"
  },
  {
    "currency": "SEK",
    "conversion": "7.90165"
  },
  {
    "currency": "SGD",
    "conversion": "1.318504"
  },
  {
    "currency": "SHP",
    "conversion": "0.707904"
  },
  {
    "currency": "SLL",
    "conversion": "7630.000339"
  },
  {
    "currency": "SOS",
    "conversion": "562.000338"
  },
  {
    "currency": "SRD",
    "conversion": "7.403664"
  },
  {
    "currency": "STD",
    "conversion": "19662.900391"
  },
  {
    "currency": "SVC",
    "conversion": "8.75037"
  },
  {
    "currency": "SYP",
    "conversion": "514.97998"
  },
  {
    "currency": "SZL",
    "conversion": "12.065038"
  },
  {
    "currency": "THB",
    "conversion": "31.43037"
  },
  {
    "currency": "TJS",
    "conversion": "8.825104"
  },
  {
    "currency": "TMT",
    "conversion": "3.41"
  },
  {
    "currency": "TND",
    "conversion": "2.372038"
  },
  {
    "currency": "TOP",
    "conversion": "2.214304"
  },
  {
    "currency": "TRY",
    "conversion": "3.768804"
  },
  {
    "currency": "TTD",
    "conversion": "6.714504"
  },
  {
    "currency": "TWD",
    "conversion": "29.298038"
  },
  {
    "currency": "TZS",
    "conversion": "2241.000336"
  },
  {
    "currency": "UAH",
    "conversion": "27.830367"
  },
  {
    "currency": "UGX",
    "conversion": "3622.000335"
  },
  {
    "currency": "USD",
    "conversion": "1"
  },
  {
    "currency": "UYU",
    "conversion": "28.370001"
  },
  {
    "currency": "UZS",
    "conversion": "8151.000335"
  },
  {
    "currency": "VEF",
    "conversion": "9.975038"
  },
  {
    "currency": "VND",
    "conversion": "22708"
  },
  {
    "currency": "VUV",
    "conversion": "102.550003"
  },
  {
    "currency": "WST",
    "conversion": "2.493104"
  },
  {
    "currency": "XAF",
    "conversion": "525.950012"
  },
  {
    "currency": "XAG",
    "conversion": "0.060181"
  },
  {
    "currency": "XAU",
    "conversion": "0.00075"
  },
  {
    "currency": "XCD",
    "conversion": "2.703606"
  },
  {
    "currency": "XDR",
    "conversion": "0.685999"
  },
  {
    "currency": "XOF",
    "conversion": "525.950012"
  },
  {
    "currency": "XPF",
    "conversion": "96.050364"
  },
  {
    "currency": "YER",
    "conversion": "249.850006"
  },
  {
    "currency": "ZAR",
    "conversion": "12.064804"
  },
  {
    "currency": "ZMK",
    "conversion": "9001.203593"
  },
  {
    "currency": "ZMW",
    "conversion": "9.803591"
  },
  {
    "currency": "ZWL",
    "conversion": "322.355011"
  }
]